pdchaos/middleware/contrib/flask/__init__.py
pdchaos/middleware/contrib/flask/config.py
pdchaos/middleware/contrib/flask/flask_middleware.py
pdchaos/middleware/contrib/flask/version.py
proofdock_chaos_middleware_flask-0.1.3.dist-info/METADATA
proofdock_chaos_middleware_flask-0.1.3.dist-info/WHEEL
proofdock_chaos_middleware_flask-0.1.3.dist-info/top_level.txt
proofdock_chaos_middleware_flask-0.1.3.dist-info/RECORD
