Metadata-Version: 2.1
Name: proofdock-chaos-middleware-flask
Version: 0.1.3
Summary: A chaos engineering framework for Python Flask applications.
Home-page: https://github.com/proofdock/chaos-middleware-python/tree/master/src/contrib-flask
Author: Proofdock Authors
Author-email: support@proofdock.io
License: Apache-2.0
Platform: UNKNOWN
Classifier: Intended Audience :: Developers
Classifier: Development Status :: 4 - Beta
Classifier: Intended Audience :: Developers
Classifier: License :: OSI Approved :: Apache Software License
Classifier: Programming Language :: Python
Classifier: Programming Language :: Python :: 3
Classifier: Programming Language :: Python :: 3.5
Classifier: Programming Language :: Python :: 3.6
Classifier: Programming Language :: Python :: 3.7
Classifier: Programming Language :: Python :: 3.8
Requires-Python: >=3.5.*
Requires-Dist: flask
Requires-Dist: proofdock-chaos-middleware-python
